Lab 04/sign.v
//sign extention
module sign(SIGNIN,SIGNOUT);
//port declaration
input [7:0] SIGNIN;
output reg [31:0] SIGNOUT;
reg [6:0] SIGNHOLD;

always @(SIGNIN) begin 
	if(SIGNIN[7]==1'b0) begin   //for positive in
		SIGNOUT = {24'b00000000_00000000_00000000,SIGNIN};
	end
	if (SIGNIN[7]== 1'b1) begin  //for negative in
		//SIGNIN[6:0] =~SIGNIN[6:0];
		SIGNHOLD = SIGNIN[6:0] ;
		
		SIGNOUT = {1'b1,24'b11111111_11111111_11111111,SIGNHOLD[6:0]};
		
		
	end
	SIGNOUT   = SIGNOUT <<< 2;  //shift left by two
end

endmodule


//adder module
module adder(D1,D2,OUT);
//port declaration
	input [31:0] D1,D2;
	output reg [31:0] OUT;


always @ (D1,D2) begin
	#2  //delay to sync with ALU
	#2  //delay for the adder
	OUT = D1 + D2;	
end	
endmodule



//and module
module and_gate(ANDIN1,ANDIN2,ANDOUT);
//port declaration
	input  ANDIN1,ANDIN2;
	output reg ANDOUT;


always @ (ANDIN1,ANDIN2) begin
	if(ANDIN1 == 1'b1 && ANDIN2 == 1'b1) begin
		ANDOUT = 1'b1;
	end	
	
	else begin
		ANDOUT = 1'b0;
	end
	
	
end
		
endmodule



























/*module sign_test;
	reg [7:0] in;

	//declaring output
	wire reg[31:0] out;
	

	//cteate alumodel for testing
	sign sign1(in,out);
	
	initial
	begin
		//generate files need to plot waveform using GTKWave
		$dumpfile("wavedata_cpu.vcd");
		$dumpvars(0,sign_test);
	end
	
	initial
	begin  
		//testing the forward answer 0100 0100
		
		
		
		in = 8'b00011100;
		#10
		in = 8'b11111111;
		#10
		in = 8'b00000001;
		#10
		in = 8'b11001110;
		#20;
		
		
		
		end
		
endmodule	*/

Lab 04/Part 4/alu.v
module alu(DATA1,DATA2,SELECT,RESULT,ZERO);
	//port declaration 
	//create 2  8 bit input
	input [7:0] DATA1 , DATA2;
	//create a 3bit input
	input [2:0] SELECT;
	//create a 8 bit output reg for hold the result
	output reg [7:0] RESULT;
	output reg ZERO;  //for branch purpose
	
	
	always @ (DATA1,DATA2,SELECT) //sensivity for data1 ,data2 and select ports
	begin
		casex (SELECT)
			3'b000 : #1 RESULT = DATA2;               //forward
 			3'b001 : #2 RESULT = DATA1 + DATA2;   //add data
			3'b010 : #1 RESULT = DATA1 & DATA2;  //bitwise and opration
			3'b011 : #1 RESULT = DATA1 | DATA2;   //bitwise or opration
			3'b1xx :    RESULT = 8'b00000000;        //reserved
		endcase
		
	end
	always @ (DATA1,DATA2,SELECT) begin
	#2
		if(DATA1-DATA2 == 0) begin
			ZERO = 1'b1;
		end
		else begin
			ZERO =1'b0;
		end
		
		
		
	end
	
endmodule

Lab 04/Part 4/cpu.v
//2s compliment moodule ******************************************
module comp(In2S,OUT2S);
	input [7:0] In2S;
	output reg [7:0] OUT2S;
	reg [7:0] pchold;
	always @ (In2S) begin	
		pchold = ~In2S;
	    pchold = pchold + 1;
		OUT2S = pchold;
	end
endmodule

//muxtiflexer module*********************************************
module mux(IN0,IN1,SEL,OUT);
	//declaring the ports
	input [7:0] IN0,IN1;
	input SEL;
	output reg [7:0] OUT;
	
	always @ (SEL,IN0,IN1) begin //set sensivity 
	if(SEL == 1'b0)begin
	OUT = IN0; 
	end
	else begin
	OUT = IN1;
	end
	end
	
endmodule

//control unit***************************************************
module ctrl_unit(INSTRUCTIONS,CLK,RESET,READREG1,READREG2,WRITEREG,WRITEENABLE,IMMIDIATE,ALUOP,MUX_immi,MUX_2s,BRANCH);

	//declareing input 
	input [31:0] INSTRUCTIONS;
	input CLK,RESET;
	//declaring output
	//output reg[31:0] PC;
	output reg [7:0] IMMIDIATE;
	output reg [2:0] READREG1,READREG2,WRITEREG,ALUOP;
	output reg MUX_immi,MUX_2s,WRITEENABLE;
	output reg BRANCH;
	//wire [31:0] PC_out;
	
	//pc module*********************************************************
	
	
	
	always @ (INSTRUCTIONS) begin
		if(INSTRUCTIONS[31:24] == 8'd0)  begin //add 
					
					WRITEREG = INSTRUCTIONS[18:16];
					READREG1 = INSTRUCTIONS[10:8];
					READREG2 = INSTRUCTIONS[2:0];
					#1
					MUX_2s = 1'b0;
					MUX_immi = 1'b1;
					WRITEENABLE = 1'b1;
					ALUOP = 3'b001;
					BRANCH = 1'b0;
					
			end
			if(INSTRUCTIONS[31:24] == 8'd1) begin //sub
					
					WRITEREG = INSTRUCTIONS[18:16];
					READREG1 = INSTRUCTIONS[10:8];
					READREG2 = INSTRUCTIONS[2:0];
					#1
					MUX_2s = 1'b1;
					MUX_immi = 1'b1;
					WRITEENABLE = 1'b1;
					ALUOP = 3'b001;
					BRANCH = 1'b0;
					end
			if(INSTRUCTIONS[31:24] == 8'd2)begin  //and
					
					WRITEREG = INSTRUCTIONS[18:16];
					READREG1 = INSTRUCTIONS[10:8];
					READREG2 = INSTRUCTIONS[2:0];
					#1
					MUX_2s = 1'b0;
					MUX_immi = 1'b1;
					WRITEENABLE = 1'b1;
					ALUOP = 3'b010;
					BRANCH = 1'b0;
					end
			
			if(INSTRUCTIONS[31:24] == 8'd3) begin //or
					
					WRITEREG = INSTRUCTIONS[18:16];
					READREG1 = INSTRUCTIONS[10:8];
					READREG2 = INSTRUCTIONS[2:0];
					#1
					MUX_2s = 1'b0;
					MUX_immi = 1'b1;
					WRITEENABLE = 1'b1;
					ALUOP = 3'b011;
					BRANCH = 1'b0;
					end
			if(INSTRUCTIONS[31:24] == 8'd4) begin  //move
					
					WRITEREG = INSTRUCTIONS[18:16];
					READREG2 = INSTRUCTIONS[2:0];
					#1
					MUX_immi = 1'b1;
					MUX_2s = 1'b0;
					WRITEENABLE = 1'b1;
					ALUOP = 3'b000;
					BRANCH = 1'b0;
					end
			
			
			if(INSTRUCTIONS[31:24] == 8'd5) begin //loadi
					
					
					WRITEREG = INSTRUCTIONS[18:16];
					IMMIDIATE = INSTRUCTIONS[7:0];
				#1
					MUX_immi = 1'b0;
					MUX_2s = 1'b0;
					WRITEENABLE = 1'b1;
					ALUOP = 3'b000;
					BRANCH = 1'b0;
					end
			
			if(INSTRUCTIONS[31:24] == 8'd6) begin //BEQ
					
					
					READREG1 = INSTRUCTIONS[10:8];
					READREG2 = INSTRUCTIONS[2:0];
					IMMIDIATE = INSTRUCTIONS[23:16];
				#1
					MUX_immi = 1'b1;
					MUX_2s = 1'b0;
					//ALUOP = 3'b001;
					BRANCH = 1'b1;
					end
					
			if(INSTRUCTIONS[31:24] == 8'd7) begin //jump
					
					
					READREG1 = INSTRUCTIONS[2:0];
					READREG2 = INSTRUCTIONS[2:0];
					IMMIDIATE = INSTRUCTIONS[23:16];
				#1
					MUX_immi = 1'b1;
					MUX_2s = 1'b0;
					//ALUOP = 3'b001;
					BRANCH = 1'b1;
					end
		
		end
endmodule

//************************CPU module***************************************
module cpu(PC,INSTRUCTIONS,CLK,RESET);
	//declaring inputs and outputs
	input [31:0] INSTRUCTIONS;
	input CLK,RESET;
	
	output reg [31:0] PC;
	//declaring wires
	
	wire reg ZERO,BRANCH;
	wire  reg GATE_OUT;
	wire [31:0] SIGNOUT;
	wire [7:0] IMMIDIATE,REGOUT1,REGOUT2,MUX_immi_out,MUX_2s_out,COMP_out,ALURESULT;
	wire [2:0] READREG1,READREG2,WRITEREG,ALUOP;
	wire WRITEENABLE,MUX_2s,MUX_immi;
	reg [31:0] pc_hold;
	initial begin   //initial settings
		
		  //initialy it is zero
		pc_hold = 32'b0;
		end
	always @(posedge CLK,posedge RESET) begin
		
		if(RESET == 1'b0  )begin  //normal mood
	
			pc_hold = pc_hold + 4; 
		end
		
		if(RESET == 1'b0 && GATE_OUT == 1'b1) begin
			
			pc_hold = pc_hold + SIGNOUT;
		
		end
		
		if(RESET == 1'b1) begin //if the reset happen
		pc_hold = -4; 
		end
		
		#1   //delay to update the pc 
		PC = pc_hold;
	end
	

//connect control unit	
	ctrl_unit ctrl_unit1(INSTRUCTIONS,CLK,RESET,READREG1,READREG2,WRITEREG,WRITEENABLE,IMMIDIATE,ALUOP,MUX_immi,MUX_2s,BRANCH);
	

//connect the register file
	reg_file reg_file1(ALURESULT, REGOUT1,REGOUT2, INSTRUCTIONS[18:16], READREG1, READREG2, WRITEENABLE, CLK, RESET);//wired direcly for parallel working
	
//2s compliment unit
	comp comp1(REGOUT2,COMP_out);
	
//mulitflexer in 2s compliment
	mux mux1(REGOUT2,COMP_out,MUX_2s,MUX_2s_out);
	
//multiflexer for immidiate value
	mux mux2(IMMIDIATE,MUX_2s_out,MUX_immi,MUX_immi_out);
	
//connect alu
	alu alu1(REGOUT1,MUX_immi_out,ALUOP,ALURESULT,ZERO);
	
//connect sign extend
		sign sign1(IMMIDIATE,SIGNOUT);
		
//connect the and gate 
	and_gate and_gate1(BRANCH,ZERO,GATE_OUT);	





endmodule

Lab 04/reg.v
module reg_file(IN, OUT1, OUT2, INADDRESS, OUT1ADDRESS, OUT2ADDRESS, WRITEENABLE, CLK, RESET);
	//port declaration 
	//create a  8 bit input port
	input [7:0] IN;
	//create 3 3bit input ports (address of the registers)
	input [2:0] INADDRESS , OUT1ADDRESS , OUT2ADDRESS;
	//create 3  1bit input ports 
	input WRITEENABLE, CLK, RESET;

	
	//create 2 8 bit output reg for hold the result
	output reg [7:0] OUT1 ,OUT2;
	reg [7:0] register[7:0];
	integer i,wflag;   //flag for write  regiter and counting variable i
	
	//***********************************************
	//when the rising edge at clock
	always @(posedge CLK)
	begin
		if(WRITEENABLE == 1'b1 & RESET == 1'b0 )  //if writtble is high,when reset is high does not write)
		begin
			wflag = 1;
			#2 register[INADDRESS] = IN;     //write data into inaddress aftert 2s delay
			
		end
		if(wflag == 1) begin  //if register update it should read aftr clk posedge
			#2   //timeing delay for reading
			if(INADDRESS==OUT1ADDRESS || INADDRESS==OUT2ADDRESS)begin
			OUT1 = register[OUT1ADDRESS];	
			OUT2 = register[OUT2ADDRESS];
			wflag = 0;
			end
		end
	end
	
	always begin 
		
	@(posedge RESET) begin//when reset is high
			i =1; //i using as a flag to avoid reading the adress at this time
			#2  //time dealy for resetting registers
			for (i =0; i < 8 ;i = i + 1) begin
				register[i] = 8'd0;
			end
			  //i also used to read regiters after the reset
	end
	
		if(i==8)begin //after updating registers are reading
		#2 //time delay for reading (registers
		OUT1 = register[OUT1ADDRESS];	
		OUT2 = register[OUT2ADDRESS];
		
		end
	end
	
	always @(OUT1ADDRESS,OUT2ADDRESS,WRITEENABLE) begin//when register address are updated registers are reading
	
		if(i != 1) begin  //if the reset happen at the same time does not run this
		#2 //time delay for reading (registers
		OUT1 = register[OUT1ADDRESS];	
		OUT2 = register[OUT2ADDRESS];
		end
	end			
endmodule

Lab 04/Part 4/cpu_test.v
module cpu_test;
	reg [31:0] INSTRUCTIONS;
	reg CLK,RESET;
	//declaring output
	wire reg[31:0] PC;
	
	reg [7:0] MEMORY[1023:0];

	//cteate alumodel for testing
	cpu cpu1(PC,INSTRUCTIONS,CLK,RESET);
	
	initial
	begin
		//generate files need to plot waveform using GTKWave
		$dumpfile("wavedata_cpu.vcd");
		$dumpvars(0,cpu_test);
	end
	
	initial
	begin  
		//testing the forward answer 0100 0100
		RESET = 1'b1;
		CLK = 1'b1;
		#10
		RESET =1'b0;
		
		
		{MEMORY[0],MEMORY[1],MEMORY[2],MEMORY[3]} =     32'b00000101000000010000000000010100; //loadi 1 #20
		{MEMORY[4],MEMORY[5],MEMORY[6],MEMORY[7]} =     32'b00000101000000100000000000010100; //loadi 2 #10
		{MEMORY[8],MEMORY[9],MEMORY[10],MEMORY[11]} =   32'b00000110_00000011_00000011_00000010; //BEQ 2 1 2  should not jump
		{MEMORY[12],MEMORY[13],MEMORY[14],MEMORY[15]} = 32'b00000110_00000010_00000001_00000010; //BEQ 2 1 2  should jump
		{MEMORY[16],MEMORY[17],MEMORY[18],MEMORY[19]} = 32'b00000100000001000000000000000011; //mov 4 3
		{MEMORY[20],MEMORY[21],MEMORY[22],MEMORY[23]} = 32'b00000001000001010000001100000010; // SUB 5 3 2
		{MEMORY[24],MEMORY[25],MEMORY[26],MEMORY[27]} = 32'b00000101000000010000000000010111; //loadi 1 #23
		{MEMORY[28],MEMORY[29],MEMORY[30],MEMORY[31]} = 32'b00000101000000100000000000001011; //loadi 2 #11
		{MEMORY[32],MEMORY[33],MEMORY[34],MEMORY[35]} = 32'b00000011_00000100_00000001_00000011; //sub 4 3
		{MEMORY[36],MEMORY[37],MEMORY[38],MEMORY[39]} = 32'b00000001_00000101_00000011_00000010; // AND 5 3 2
		{MEMORY[40],MEMORY[41],MEMORY[42],MEMORY[43]} = 32'b00000111_11111100_0000000100000010; //jump -4
		
		end
		always @(PC) begin
			#2
			INSTRUCTIONS = {MEMORY[PC],MEMORY[PC+1],MEMORY[PC+2],MEMORY[PC+3]} ; //instruction fettiching
		
		end
	always begin
	 #5 CLK = ~CLK; //clk signal
	end
	
	
	always begin
	#25
	RESET = 1'b1;
	#12
	RESET = 1'b0;
	#110
	$finish;
	end
endmodule

Lab 04/Part 4/wavedata_cpu.vcd
$date
	Fri May 15 22:05:51 2020
$end
$version
	Icarus Verilog
$end
$timescale
	1s
$end
$scope module cpu_test $end
$var wire 32 ! PC [31:0] $end
$var reg 1 " CLK $end
$var reg 32 # INSTRUCTIONS [31:0] $end
$var reg 1 $ RESET $end
$scope module cpu1 $end
$var wire 1 " CLK $end
$var wire 32 % INSTRUCTIONS [31:0] $end
$var wire 1 $ RESET $end
$var wire 1 & ZERO $end
$var wire 3 ' WRITEREG [2:0] $end
$var wire 1 ( WRITEENABLE $end
$var wire 32 ) SIGNOUT [31:0] $end
$var wire 8 * REGOUT2 [7:0] $end
$var wire 8 + REGOUT1 [7:0] $end
$var wire 3 , READREG2 [2:0] $end
$var wire 3 - READREG1 [2:0] $end
$var wire 8 . MUX_immi_out [7:0] $end
$var wire 1 / MUX_immi $end
$var wire 8 0 MUX_2s_out [7:0] $end
$var wire 1 1 MUX_2s $end
$var wire 8 2 IMMIDIATE [7:0] $end
$var wire 1 3 GATE_OUT $end
$var wire 8 4 COMP_out [7:0] $end
$var wire 1 5 BRANCH $end
$var wire 8 6 ALURESULT [7:0] $end
$var wire 3 7 ALUOP [2:0] $end
$var reg 32 8 PC [31:0] $end
$var reg 32 9 pc_hold [31:0] $end
$scope module alu1 $end
$var wire 3 : SELECT [2:0] $end
$var wire 8 ; DATA2 [7:0] $end
$var wire 8 < DATA1 [7:0] $end
$var reg 8 = RESULT [7:0] $end
$var reg 1 & ZERO $end
$upscope $end
$scope module and_gate1 $end
$var wire 1 & ANDIN2 $end
$var wire 1 5 ANDIN1 $end
$var reg 1 3 ANDOUT $end
$upscope $end
$scope module comp1 $end
$var wire 8 > In2S [7:0] $end
$var reg 8 ? OUT2S [7:0] $end
$var reg 8 @ pchold [7:0] $end
$upscope $end
$scope module ctrl_unit1 $end
$var wire 1 " CLK $end
$var wire 32 A INSTRUCTIONS [31:0] $end
$var wire 1 $ RESET $end
$var reg 3 B ALUOP [2:0] $end
$var reg 1 5 BRANCH $end
$var reg 8 C IMMIDIATE [7:0] $end
$var reg 1 1 MUX_2s $end
$var reg 1 / MUX_immi $end
$var reg 3 D READREG1 [2:0] $end
$var reg 3 E READREG2 [2:0] $end
$var reg 1 ( WRITEENABLE $end
$var reg 3 F WRITEREG [2:0] $end
$upscope $end
$scope module mux1 $end
$var wire 8 G IN1 [7:0] $end
$var wire 1 1 SEL $end
$var wire 8 H IN0 [7:0] $end
$var reg 8 I OUT [7:0] $end
$upscope $end
$scope module mux2 $end
$var wire 8 J IN0 [7:0] $end
$var wire 8 K IN1 [7:0] $end
$var wire 1 / SEL $end
$var reg 8 L OUT [7:0] $end
$upscope $end
$scope module reg_file1 $end
$var wire 1 " CLK $end
$var wire 8 M IN [7:0] $end
$var wire 3 N INADDRESS [2:0] $end
$var wire 3 O OUT1ADDRESS [2:0] $end
$var wire 3 P OUT2ADDRESS [2:0] $end
$var wire 1 $ RESET $end
$var wire 1 ( WRITEENABLE $end
$var reg 8 Q OUT1 [7:0] $end
$var reg 8 R OUT2 [7:0] $end
$var integer 32 S i [31:0] $end
$var integer 32 T wflag [31:0] $end
$upscope $end
$scope module sign1 $end
$var wire 8 U SIGNIN [7:0] $end
$var reg 7 V SIGNHOLD [6:0] $end
$var reg 32 W SIGNOUT [31:0] $end
$upscope $end
$upscope $end
$upscope $end
$enddefinitions $end
#0
$dumpvars
bx W
bx V
bx U
bx T
b1 S
bx R
bx Q
bx P
bx O
bx N
bx M
bx L
bx K
bx J
bx I
bx H
bx G
bx F
bx E
bx D
bx C
bx B
bx A
bx @
bx ?
bx >
bx =
bx <
bx ;
bx :
b11111111111111111111111111111100 9
bx 8
bx 7
bx 6
x5
bx 4
x3
bx 2
x1
bx 0
x/
bx .
bx -
bx ,
bx +
bx *
bx )
x(
bx '
x&
bx %
1$
bx #
1"
bx !
$end
#1
b11111111111111111111111111111100 !
b11111111111111111111111111111100 8
#2
b1000 S
#5
0"
#10
b0 9
1"
0$
#11
b0 !
b0 8
#13
b1010000 )
b1010000 W
b1 N
b10100 2
b10100 C
b10100 J
b10100 U
b1 '
b1 F
b101000000010000000000010100 #
b101000000010000000000010100 %
b101000000010000000000010100 A
#14
03
b10100 .
b10100 ;
b10100 L
05
b0 7
b0 :
b0 B
1(
01
0/
#15
b10100 6
b10100 =
b10100 M
0"
#16
0&
#20
b1 T
b100 9
1"
#21
b100 !
b100 8
#23
b10 N
b10 '
b10 F
b101000000100000000000010100 #
b101000000100000000000010100 %
b101000000100000000000010100 A
#25
b1 S
b11111111111111111111111111111100 9
0"
1$
#26
b11111111111111111111111111111100 !
b11111111111111111111111111111100 8
#27
b1000 S
#28
bx N
bx #
bx %
bx A
#30
1"
#35
0"
#37
0$
#40
b0 9
1"
#41
b0 !
b0 8
#43
b1 N
b1 '
b1 F
b101000000010000000000010100 #
b101000000010000000000010100 %
b101000000010000000000010100 A
#45
0"
#50
b100 9
1"
#51
b100 !
b100 8
#53
b10 N
b10 '
b10 F
b101000000100000000000010100 #
b101000000100000000000010100 %
b101000000100000000000010100 A
#55
0"
#60
b1000 9
1"
#61
b1000 !
b1000 8
#63
b11 .
b11 ;
b11 L
b1100 )
b1100 W
b11 N
b11 2
b11 C
b11 J
b11 U
b10 ,
b10 E
b10 P
b11 -
b11 D
b11 O
b110000000110000001100000010 #
b110000000110000001100000010 %
b110000000110000001100000010 A
#64
b10100 .
b10100 ;
b10100 L
b11101100 4
b11101100 ?
b11101100 G
b11101100 @
b10100 0
b10100 I
b10100 K
b11 6
b11 =
b11 M
15
1/
b0 T
b10100 *
b10100 >
b10100 H
b10100 R
b0 +
b0 <
b0 Q
#65
b10100 6
b10100 =
b10100 M
0"
#70
b1 T
b1100 9
1"
#71
b1100 !
b1100 8
#73
b1000 )
b1000 W
b10 N
b10 2
b10 C
b10 J
b10 U
b1 -
b1 D
b1 O
b110000000100000000100000010 #
b110000000100000000100000010 %
b110000000100000000100000010 A
#74
b0 T
b10100 +
b10100 <
b10100 Q
#75
0"
#76
13
1&
#80
b1 T
b11000 9
1"
#81
b11000 !
b11000 8
#83
b1011100 )
b1011100 W
b1 N
b10111 2
b10111 C
b10111 J
b10111 U
b1 '
b1 F
b101000000010000000000010111 #
b101000000010000000000010111 %
b101000000010000000000010111 A
#84
03
b10111 .
b10111 ;
b10111 L
05
0/
b0 T
#85
b10111 6
b10111 =
b10111 M
0"
#86
0&
#90
b1 T
b11100 9
1"
#91
b11100 !
b11100 8
#93
b1011 .
b1011 ;
b1011 L
b101100 )
b101100 W
b10 N
b1011 2
b1011 C
b1011 J
b1011 U
b10 '
b10 F
b101000000100000000000001011 #
b101000000100000000000001011 %
b101000000100000000000001011 A
#94
b1011 6
b1011 =
b1011 M
b0 T
b10111 +
b10111 <
b10111 Q
#95
0"
#100
b1 T
b100000 9
1"
#101
b100000 !
b100000 8
#103
b100 N
b11 ,
b11 E
b11 P
b100 '
b100 F
b11000001000000000100000011 #
b11000001000000000100000011 %
b11000001000000000100000011 A
#104
b10100 .
b10100 ;
b10100 L
b11 7
b11 :
b11 B
1/
#105
b10111 6
b10111 =
b10111 M
0"
#110
b100100 9
1"
#111
b100100 !
b100100 8
#113
b101 N
b10 ,
b10 E
b10 P
b11 -
b11 D
b11 O
b101 '
b101 F
b1000001010000001100000010 #
b1000001010000001100000010 %
b1000001010000001100000010 A
#114
b11101100 .
b11101100 ;
b11101100 L
b11101100 0
b11101100 I
b11101100 K
b1 7
b1 :
b1 B
11
#115
b11110101 .
b11110101 ;
b11110101 L
b11110101 0
b11110101 I
b11110101 K
b11110101 4
b11110101 ?
b11110101 G
b11110101 @
b1011 *
b1011 >
b1011 H
b1011 R
b10100 +
b10100 <
b10100 Q
0"
#116
b1001 6
b1001 =
b1001 M
#120
b101000 9
1"
#121
b101000 !
b101000 8
#123
b11111111111111111111111111110000 )
b11111111111111111111111111110000 W
b1111100 V
b100 N
b11111100 2
b11111100 C
b11111100 J
b11111100 U
b10 -
b10 D
b10 O
b111111111000000000100000010 #
b111111111000000000100000010 %
b111111111000000000100000010 A
#124
b1011 .
b1011 ;
b1011 L
b1011 0
b1011 I
b1011 K
15
01
#125
b1011 +
b1011 <
b1011 Q
0"
#126
13
1&
b10110 6
b10110 =
b10110 M
#130
b11100 9
1"
#131
b11100 !
b11100 8
#133
b101100 )
b101100 W
b10 N
b1011 2
b1011 C
b1011 J
b1011 U
b10 '
b10 F
b101000000100000000000001011 #
b101000000100000000000001011 %
b101000000100000000000001011 A
#134
03
05
b0 7
b0 :
b0 B
0/
b0 T
#135
b1011 6
b1011 =
b1011 M
0"
#140
b1 T
b100000 9
1"
#141
b100000 !
b100000 8
#143
b100 N
b11 ,
b11 E
b11 P
b1 -
b1 D
b1 O
b100 '
b100 F
b11000001000000000100000011 #
b11000001000000000100000011 %
b11000001000000000100000011 A
#144
b11 7
b11 :
b11 B
1/
#145
b10100 .
b10100 ;
b10100 L
b11101100 4
b11101100 ?
b11101100 G
b11101100 @
b10100 0
b10100 I
b10100 K
b11111 6
b11111 =
b11111 M
b10100 *
b10100 >
b10100 H
b10100 R
b10111 +
b10111 <
b10111 Q
0"
#146
b10111 6
b10111 =
b10111 M
0&
