Lab 04/Part 3/alu.v
//module for alu
module alu(DATA1, DATA2, RESULT,SELECT);			
	input [0:7]DATA1;
	input [0:7]DATA2;
	input [0:2]SELECT;						//inputs
	output [0:7]RESULT;						//out put result

	reg [0:7]RESULT;
	always @ (DATA1,DATA2,SELECT)	#1	//done it whe there is a change in values and do the operation with 1 time interval delay
	begin
		if (SELECT==3'b000)   begin			//for the forward
		//for the FOWARD function
			RESULT= DATA2;

		end if (SELECT==3'b001)   #1 begin
		//for the ADD and SUB function
			RESULT=DATA1+DATA2;

		end if (SELECT==3'b010) #1 begin
		//for the AND function
			RESULT= DATA1 & DATA2;

		end if(SELECT==3'b011) #1 begin
		//for the OR function
			RESULT=DATA1 | DATA2;

		end 
	end
endmodule

Lab 04/Part 3/sub_mux.v
//module for mux
module sub_mux(IN0,IN1,SELECT,OUT);
	input [7:0] IN0,IN1;
	output [7:0] OUT;
	input SELECT;
	reg [7:0] OUT;
	
	always @(SELECT,IN0,IN1)  
	begin
		if (SELECT==0) begin
			OUT= IN0;
		end if (SELECT==1) begin
			OUT=IN1;
		end
	end
endmodule

Lab 04/Part 3/2s_complement.v
//module for converting 2s complement
module complement(IN,OUT);
	input [7:0] IN;
	output [7:0] OUT;
	reg [7:0] OUT;
	integer i;
	always @(IN)
	begin
		//invert all bits
		for (i=0;i<8;i=i+1) begin
			if (IN[i]==0) begin
				OUT[i]=1;
			end if (IN[i]==1) begin
				OUT[i]=0;
			end
		end
		//adding binary one for final value
		OUT=OUT+8'b00000001;
	end
	
endmodule

Lab 04/Part 3/reg_file.v

//module for reg file
module reg_file
  (input clk,
   input reset,
   input write,
   input [2:0] writeAddr,
   input [7:0] writeData,
   input [2:0] readAddrA,
   output [7:0] readDataA,
   input [2:0] readAddrB,
   output [7:0] readDataB);

   //give reg file 8 bit reg
   reg [7:0] 	 regfile [0:7];

   //assigning the data with the 2 time delay
   assign #2 readDataA = regfile[readAddrA];
   assign #2 readDataB = regfile[readAddrB];
   

   always @(posedge clk)  begin    		
       
	 if (write) #2 regfile[writeAddr] <= writeData ;		//erite data in to reg file
      // else: !if(reset)
	end
   always @(posedge reset)  begin				//reset with the delay
	 regfile[0] <= 0;
	 regfile[1] <= 0;
	 regfile[2] <= 0;
	 regfile[3] <= 0;
	 regfile[4] <= 0;
	 regfile[5] <= 0;
	 regfile[6] <= 0;
	 regfile[7] <= 0;
    end
endmodule

Lab 04/Part 3/instruction.v
//module for instruction genaration 
module instruction_gen(PC,INSTRUCTION);
	input [31:0] PC;
	output [31:0] INSTRUCTION;
	reg [31:0] memory[6:0];
	wire [6:0] rom_adr = PC[5:2];
	
	initial
	begin
		$readmemb("test.prog",memory,0,6);				//read the file of instruction
	end
	assign #2 INSTRUCTION = memory[rom_adr];	//put te instruction in to reg
endmodule

Lab 04/Part 3/pc.v
//module for programme counter
module pc(CLK,RESET,OUT);
	input CLK,RESET;
	output [31:0] OUT;
	reg [31:0] IN,IN2;
	
	//sete the IN 2 OUT
	assign  OUT=IN2;

	always @(posedge CLK) #1 begin 
		IN2<=IN;
		
		//increment the value
		#2 IN<=IN+32'h00000004;
			
	end
	always @(posedge RESET) #1 begin
		if (RESET)  #2
			IN<=32'h00000000;
			
	end
	//assign  OUT=IN;
endmodule

Lab 04/Part 3/main_control.v
`include "instruction.v"
`include "pc.v"

//Module fore main control
module main_control(
	input CLK,
	input RESET,
	output [2:0] ALU_OP,
	output SUB_SELECT,
	output IMMEDIATAE_SELECT,
	output WRITE,
	output [7:0 ]IMMEDIATAE,
	output [2:0] OUT1_ADD,
	output [2:0] OUT2_ADD,
	output [2:0] WRITE_ADD
	);
	wire [31:0] PC,INSTRUCTION;
	reg IMMEDIATAE_SELECT,SUB_SELECT;
	reg [2:0] ALU_OP;
	
	pc program_counter(CLK,RESET,PC);
	instruction_gen myinstruction_gen(PC,INSTRUCTION);
	
	//decoding for next operatios
	assign #1 WRITE=1;
	assign #1 IMMEDIATAE= INSTRUCTION[7:0];
	assign  OUT1_ADD= INSTRUCTION[10:8];
	assign  OUT2_ADD= INSTRUCTION[2:0];
	assign  WRITE_ADD= INSTRUCTION[18:16];
	//decoding ALUopp and selects for muxes
	always @(INSTRUCTION) #1 begin
		if (INSTRUCTION[27:24]==4'b0000) begin
			IMMEDIATAE_SELECT=1'b1;   		//for load instruction give the emmediate select=1
		end
		if (INSTRUCTION[27:24]!=4'b0000) begin
			IMMEDIATAE_SELECT=1'b0;
		end
		if (INSTRUCTION[26:24]==3'b011) begin
			SUB_SELECT=1'b1;						//for the subtract give the sub select=1
		end
		if (INSTRUCTION[26:24]!=3'b011) begin
			SUB_SELECT=1'b0;
		end
		//ALU_OP decoding
		if (INSTRUCTION[27:24]==4'b0000) begin
			ALU_OP=3'b000;							//for load
		end
		if (INSTRUCTION[27:24]==4'b0001) begin
			ALU_OP=3'b000;							//for move 
		end
		if (INSTRUCTION[27:24]==4'b0010) begin
			ALU_OP=3'b001;							//for add
		end
		if (INSTRUCTION[27:24]==4'b0011) begin
			ALU_OP=3'b001;							//dor sub				
		end
		if (INSTRUCTION[27:24]==4'b0100) begin
			ALU_OP=3'b010;							//for AND
		end
		if (INSTRUCTION[27:24]==4'b0101) begin
			ALU_OP=3'b011;
		end
	end
	
endmodule

Lab 04/Part 3/cpu.v
`include "main_control.v"
`include  "2s_complement.v" 
`include "sub_mux.v"
`include "alu.v"
`include "reg_file.v"
module cpu(CLK,RESET);
	input CLK,RESET;
	wire [7:0] IMMEDIATAE,ALU_RESULT,REG_OUT1,REG_OUT2,COMPLEMENT,RES1,OPERAND1;
	wire [2:0] ALU_OPP,OUT1_ADD,OUT2_ADD,WRITE_ADD;
	wire SUB_SELECT,IMMEDIATAE_SELECT,WRITE;
	
	main_control my_main_control(CLK,RESET, ALU_OPP,SUB_SELECT,IMMEDIATAE_SELECT, WRITE,IMMEDIATAE,OUT1_ADD,OUT2_ADD,WRITE_ADD);
	reg_file #1 myreg (CLK,RESET,WRITE,WRITE_ADD,ALU_RESULT,OUT1_ADD,REG_OUT1,OUT2_ADD,REG_OUT2);
	complement mycomp(REG_OUT2,COMPLEMENT);
	sub_mux mysub(REG_OUT2,COMPLEMENT,SUB_SELECT,RES1);
	sub_mux #1 myimmediate(RES1,IMMEDIATAE,IMMEDIATAE_SELECT,OPERAND1);
	alu #1 myalu (REG_OUT1,OPERAND1,ALU_RESULT,ALU_OPP);
	
endmodule

Lab 04/Part 3/test_bench.v
`include "cpu.v"
//test bench
module test_bench;
	reg CLK,RESET;
	cpu mycpu(CLK,RESET);
	initial
	begin
		//$monitor($time,"inpt=%b     oypt=%b   seleje=%b",in,result,select);
		$dumpfile("wavedata12.vcd");
		$dumpvars(0, test_bench);
		CLK=1'b1;
		#3
		RESET=1'b1;
		#5
		RESET=1'b0;
		#75
		$finish;
	end
	always
        #5 CLK = ~CLK;				//CLK value
endmodule

Lab 04/Part 3/wavedata12.vcd
$date
	Fri May 15 11:11:51 2020
$end
$version
	Icarus Verilog
$end
$timescale
	1s
$end
$scope module test_bench $end
$var reg 1 ! CLK $end
$var reg 1 " RESET $end
$scope module mycpu $end
$var wire 1 ! CLK $end
$var wire 1 " RESET $end
$var wire 1 # WRITE $end
$var wire 3 $ WRITE_ADD [2:0] $end
$var wire 1 % SUB_SELECT $end
$var wire 8 & RES1 [7:0] $end
$var wire 8 ' REG_OUT2 [7:0] $end
$var wire 8 ( REG_OUT1 [7:0] $end
$var wire 3 ) OUT2_ADD [2:0] $end
$var wire 3 * OUT1_ADD [2:0] $end
$var wire 8 + OPERAND1 [7:0] $end
$var wire 1 , IMMEDIATAE_SELECT $end
$var wire 8 - IMMEDIATAE [7:0] $end
$var wire 8 . COMPLEMENT [7:0] $end
$var wire 8 / ALU_RESULT [7:0] $end
$var wire 3 0 ALU_OPP [2:0] $end
$scope module my_main_control $end
$var wire 1 ! CLK $end
$var wire 1 " RESET $end
$var wire 1 # WRITE $end
$var wire 3 1 WRITE_ADD [2:0] $end
$var wire 32 2 PC [31:0] $end
$var wire 3 3 OUT2_ADD [2:0] $end
$var wire 3 4 OUT1_ADD [2:0] $end
$var wire 32 5 INSTRUCTION [31:0] $end
$var wire 8 6 IMMEDIATAE [7:0] $end
$var reg 3 7 ALU_OP [2:0] $end
$var reg 1 , IMMEDIATAE_SELECT $end
$var reg 1 % SUB_SELECT $end
$scope module myinstruction_gen $end
$var wire 32 8 INSTRUCTION [31:0] $end
$var wire 7 9 rom_adr [6:0] $end
$var wire 32 : PC [31:0] $end
$upscope $end
$scope module program_counter $end
$var wire 1 ! CLK $end
$var wire 32 ; OUT [31:0] $end
$var wire 1 " RESET $end
$var reg 32 < IN [31:0] $end
$var reg 32 = IN2 [31:0] $end
$upscope $end
$upscope $end
$scope module myalu $end
$var wire 3 > SELECT [0:2] $end
$var wire 8 ? DATA2 [0:7] $end
$var wire 8 @ DATA1 [0:7] $end
$var reg 8 A RESULT [0:7] $end
$upscope $end
$scope module mycomp $end
$var wire 8 B IN [7:0] $end
$var reg 8 C OUT [7:0] $end
$var integer 32 D i [31:0] $end
$upscope $end
$scope module myimmediate $end
$var wire 8 E IN1 [7:0] $end
$var wire 1 , SELECT $end
$var wire 8 F IN0 [7:0] $end
$var reg 8 G OUT [7:0] $end
$upscope $end
$scope module myreg $end
$var wire 1 ! clk $end
$var wire 3 H readAddrA [2:0] $end
$var wire 3 I readAddrB [2:0] $end
$var wire 8 J readDataA [7:0] $end
$var wire 8 K readDataB [7:0] $end
$var wire 1 " reset $end
$var wire 1 # write $end
$var wire 3 L writeAddr [2:0] $end
$var wire 8 M writeData [7:0] $end
$upscope $end
$scope module mysub $end
$var wire 8 N IN0 [7:0] $end
$var wire 8 O IN1 [7:0] $end
$var wire 1 % SELECT $end
$var reg 8 P OUT [7:0] $end
$upscope $end
$upscope $end
$upscope $end
$enddefinitions $end
#0
$dumpvars
bx P
bx O
bx N
bx M
bx L
bx K
bx J
bx I
bx H
bx G
bx F
bx E
bx D
bx C
bx B
bx A
bx @
bx ?
bx >
bx =
bx <
bx ;
bx :
b0xxxx 9
bx 8
bx 7
bx 6
bx 5
bx 4
bx 3
bx 2
bx 1
bx 0
bx /
bx .
bx -
x,
bx +
bx *
bx )
bx (
bx '
bx &
x%
bx $
x#
x"
1!
$end
#1
1#
#3
1"
#5
0!
#6
b0 <
#8
0"
#10
1!
#11
b0 9
b0 2
b0 :
b0 ;
b0 =
#13
b100 <
b1 $
b1 1
b1 L
b111 )
b111 3
b111 I
b0 *
b0 4
b0 H
b10000000011110111 5
b10000000011110111 8
#14
b11110111 +
b11110111 ?
b11110111 G
b11110111 -
b11110111 6
b11110111 E
b0 0
b0 7
b0 >
0%
1,
#15
b0 .
b0 C
b0 O
b1000 D
b0 &
b0 F
b0 P
b11110111 /
b11110111 A
b11110111 M
b0 '
b0 B
b0 K
b0 N
b0 (
b0 @
b0 J
0!
#20
1!
#21
b1 9
b100 2
b100 :
b100 ;
b100 =
#23
b1000 <
b0 $
b0 1
b0 L
b11 )
b11 3
b11 I
b100011 5
b100011 8
#24
b100011 +
b100011 ?
b100011 G
b100011 -
b100011 6
b100011 E
#25
b100011 /
b100011 A
b100011 M
0!
#30
1!
#31
b10 9
b1000 2
b1000 :
b1000 ;
b1000 =
#33
b1100 <
b10 $
b10 1
b10 L
b0 )
b0 3
b0 I
b1 *
b1 4
b1 H
b10000000100000000100000000 5
b10000000100000000100000000 8
#34
b0 +
b0 ?
b0 G
b0 -
b0 6
b0 E
b1 0
b1 7
b1 >
0,
#35
b100011 +
b100011 ?
b100011 G
b11011101 .
b11011101 C
b11011101 O
b1000 D
b100011 &
b100011 F
b100011 P
b100011 '
b100011 B
b100011 K
b100011 N
b11110111 (
b11110111 @
b11110111 J
0!
#36
b11010 /
b11010 A
b11010 M
#40
1!
#41
b11 9
b1100 2
b1100 :
b1100 ;
b1100 =
#43
b10000 <
b11 $
b11 1
b11 L
b1 )
b1 3
b1 I
b10 *
b10 4
b10 H
b11000000110000001000000001 5
b11000000110000001000000001 8
#44
b11011101 +
b11011101 ?
b11011101 G
b11011101 &
b11011101 F
b11011101 P
b1 -
b1 6
b1 E
1%
#45
b1001 +
b1001 ?
b1001 G
b1001 &
b1001 F
b1001 P
b1001 .
b1001 C
b1001 O
b1000 D
b11110111 '
b11110111 B
b11110111 K
b11110111 N
b11010 (
b11010 @
b11010 J
0!
#46
b100011 /
b100011 A
b100011 M
#50
1!
#51
b100 9
b10000 2
b10000 :
b10000 ;
b10000 =
#53
b10100 <
b100 $
b100 1
b100 L
b11 )
b11 3
b11 I
b0 *
b0 4
b0 H
b1000001000000000000000011 5
b1000001000000000000000011 8
#54
b11110111 +
b11110111 ?
b11110111 G
b11110111 &
b11110111 F
b11110111 P
b11 -
b11 6
b11 E
b0 0
b0 7
b0 >
0%
#55
b100011 +
b100011 ?
b100011 G
b11011101 .
b11011101 C
b11011101 O
b1000 D
b100011 &
b100011 F
b100011 P
b11110111 /
b11110111 A
b11110111 M
b100011 '
b100011 B
b100011 K
b100011 N
b100011 (
b100011 @
b100011 J
0!
#56
b100011 /
b100011 A
b100011 M
#60
1!
#61
b101 9
b10100 2
b10100 :
b10100 ;
b10100 =
#63
b11000 <
b101 $
b101 1
b101 L
b100 )
b100 3
b100 I
b1 *
b1 4
b1 H
b100000001010000000100000100 5
b100000001010000000100000100 8
#64
b100 -
b100 6
b100 E
b10 0
b10 7
b10 >
#65
b11110111 (
b11110111 @
b11110111 J
0!
#70
1!
#71
b110 9
b11000 2
b11000 :
b11000 ;
b11000 =
#73
b11100 <
b111 $
b111 1
b111 L
b10 )
b10 3
b10 I
b11 *
b11 4
b11 H
b101000001110000001100000010 5
b101000001110000001100000010 8
#74
b10 -
b10 6
b10 E
b11 0
b11 7
b11 >
#75
b11010 +
b11010 ?
b11010 G
b11100110 .
b11100110 C
b11100110 O
b1000 D
b11010 &
b11010 F
b11010 P
b11010 '
b11010 B
b11010 K
b11010 N
b100011 (
b100011 @
b100011 J
0!
#76
b111011 /
b111011 A
b111011 M
#80
1!
#81
b111 9
b11100 2
b11100 :
b11100 ;
b11100 =
#83
b100000 <
bx $
bx 1
bx L
bx )
bx 3
bx I
bx *
bx 4
bx H
bx 5
bx 8
