Lab 04/Part 2/reg_file.v
// Computer Architecture (CO224) - Lab 05 part 2
//e16319 Ratnayake R.P.V.N

//test bench for the register file
module reg_file_tb;
    
    reg [7:0] WRITEDATA;
    reg [2:0] WRITEREG, READREG1, READREG2;
    reg CLK, RESET, WRITEENABLE; 
    wire [7:0] REGOUT1, REGOUT2;
    
    reg_file myregfile(CLK,RESET,WRITEENABLE,WRITEREG,WRITEDATA,READREG1,REGOUT1,READREG2,REGOUT2);
       
    initial
    begin
        CLK = 1'b1;
        
        // generate files needed to plot the waveform using GTKWave
        $dumpfile("reg_file_wavedata.vcd");
		$dumpvars(0, reg_file);
        
        // assign values with time to input signals to see output 
        RESET = 1'b0;
        WRITEENABLE = 1'b0;
        
        #1
        RESET = 1'b1;
        READREG1 = 3'd0;
        READREG2 = 3'd4;
        
        #8
        RESET = 1'b0;
        
        #5
        WRITEREG = 3'd3;
        WRITEDATA = 8'd35;
        WRITEENABLE = 1'b1;
        
        #10
        WRITEENABLE = 1'b0;
        
        #1
        READREG1 = 3'd3;
        
        #9
        WRITEREG = 3'd1;
        WRITEDATA = 8'd53;

        WRITEENABLE = 1'b1;
        READREG1 = 3'd1;
        
        #10
        WRITEENABLE = 1'b0;
        
        #10
        WRITEREG = 3'd4;
        WRITEDATA = 8'd98;
        WRITEENABLE = 1'b1;
        
        #10
        WRITEDATA = 8'd15;
        WRITEENABLE = 1'b1;
        
        #10
        WRITEENABLE = 1'b0;
        
        #6
        WRITEREG = 3'd1;
        WRITEDATA = 8'd50;
        WRITEENABLE = 1'b1;
        
        #5
        WRITEENABLE = 1'b0;

        #8
        WRITEREG = 3'd3;
        WRITEDATA = 8'd36;
        WRITEENABLE = 1'b1;
        
        #5
        WRITEENABLE = 1'b0;

        #1
        READREG1 = 3'd3;
        READREG2 = 3'd7;

        #5
        WRITEREG = 3'd7;
        WRITEDATA = 8'd24;
        WRITEENABLE = 1'b1;

        #10
        WRITEENABLE = 1'b0;

        #10
        $finish;
    end
    
    
    // clock signal generation
    always
        #5 CLK = ~CLK;

    always @ (WRITEREG,CLK)
    	#5 ;

endmodule

//module for reg file
module reg_file
  (input clk,
   input reset,
   input write,
   input [2:0] writeAddr,
   input [7:0] writeData,
   input [2:0] readAddrA,
   output [7:0] readDataA,
   input [2:0] readAddrB,
   output [7:0] readDataB);

   //give reg file 8 bit reg
   reg [7:0] 	 regfile [0:7];

   //assigning the data with the 2 time delay
   assign #2 readDataA = regfile[readAddrA];
   assign #2 readDataB = regfile[readAddrB];

   always @(posedge clk) #2 begin    		
      if (reset) #1 begin				//reset with the delay
	 regfile[0] <= 0;
	 regfile[1] <= 0;
	 regfile[2] <= 0;
	 regfile[3] <= 0;
	 regfile[4] <= 0;
	 regfile[5] <= 0;
	 regfile[6] <= 0;
	 regfile[7] <= 0;
      end else  begin 
	 if  (write) regfile[writeAddr] <= writeData ;		//erite data in to reg file
      end // else: !if(reset)
   end
endmodule

Lab 04/Part 2/reg_file_wavedata.vcd
$date
	Sat May  9 15:50:53 2020
$end
$version
	Icarus Verilog
$end
$timescale
	1s
$end
$scope module reg_file_tb $end
$var wire 8 ! REGOUT2 [7:0] $end
$var wire 8 " REGOUT1 [7:0] $end
$var reg 1 # CLK $end
$var reg 3 $ READREG1 [2:0] $end
$var reg 3 % READREG2 [2:0] $end
$var reg 1 & RESET $end
$var reg 8 ' WRITEDATA [7:0] $end
$var reg 1 ( WRITEENABLE $end
$var reg 3 ) WRITEREG [2:0] $end
$scope module myregfile $end
$var wire 1 # clk $end
$var wire 3 * readAddrA [2:0] $end
$var wire 3 + readAddrB [2:0] $end
$var wire 8 , readDataA [7:0] $end
$var wire 8 - readDataB [7:0] $end
$var wire 1 & reset $end
$var wire 1 ( write $end
$var wire 3 . writeAddr [2:0] $end
$var wire 8 / writeData [7:0] $end
$upscope $end
$upscope $end
$enddefinitions $end
#0
$dumpvars
bx /
bx .
bx -
bx ,
bx +
bx *
bx )
0(
bx '
0&
bx %
bx $
1#
bx "
bx !
$end
#1
b100 %
b100 +
b0 $
b0 *
1&
#5
b0 !
b0 -
b0 "
b0 ,
0#
#9
0&
#10
1#
#14
1(
b100011 '
b100011 /
b11 )
b11 .
#15
0#
#20
1#
#24
0(
#25
b11 $
b11 *
0#
#27
b100011 "
b100011 ,
#30
1#
#34
b1 $
b1 *
1(
b110101 '
b110101 /
b1 )
b1 .
#35
0#
#36
b0 "
b0 ,
#40
1#
#44
b110101 "
b110101 ,
0(
#45
0#
#50
1#
#54
1(
b1100010 '
b1100010 /
b100 )
b100 .
#55
0#
#60
1#
#64
b1100010 !
b1100010 -
b1111 '
b1111 /
#65
0#
#70
1#
#74
b1111 !
b1111 -
0(
#75
0#
#80
1#
1(
b110010 '
b110010 /
b1 )
b1 .
#84
b110010 "
b110010 ,
#85
0#
0(
#90
1#
#93
1(
b100100 '
b100100 /
b11 )
b11 .
#95
0#
#98
0(
#99
b111 %
b111 +
b11 $
b11 *
#100
1#
#101
b0 !
b0 -
b100011 "
b100011 ,
#104
1(
b11000 '
b11000 /
b111 )
b111 .
#105
0#
#110
1#
#114
b11000 !
b11000 -
0(
